{"status":200,"message":"success","data":{"items":[{"article_id":74,"article_cat_id":2,"title":"测试B","image":"careyshop.oruei.com\/uploads\/files\/20191206\/47a84479bcfa0c379cc40a37febb4f9a.png?type=careyshop","source":"","source_url":"","keywords":"","description":"","url":"http:\/\/www.baidu.com","target":"_self","page_views":106,"is_top":1,"status":1,"create_time":"2017-07-13 23:29:23","update_time":"2019-12-06 22:29:54","get_article_cat":{"cat_name":"配送查询","cat_type":0}},{"article_id":73,"article_cat_id":3,"title":"el-cascader的使用以及报错解决","image":"aliyun.oss.careyshop.cn\/uploads\/files\/20191112\/968cc6c2-b121-4d4c-804e-cf828af7e1fb.jpg?type=aliyun","source":"","source_url":"","keywords":"","description":"","url":"","target":"_self","page_views":225,"is_top":0,"status":0,"create_time":"2017-07-13 23:27:38","update_time":"2020-05-12 13:52:10","get_article_cat":{"cat_name":"配送服务","cat_type":0}},{"article_id":72,"article_cat_id":4,"title":"测试666","image":"aliyun.oss.careyshop.cn\/uploads\/files\/20191112\/2c82bed2-233d-45e5-8752-d169b8265ee6.jpg?type=aliyun","source":"","source_url":"","keywords":"","description":"","url":"","target":"_self","page_views":105,"is_top":1,"status":1,"create_time":"2017-07-13 23:27:36","update_time":"2019-11-13 13:55:20","get_article_cat":{"cat_name":"配送费用","cat_type":0}},{"article_id":71,"article_cat_id":5,"title":"测试","image":"","source":"","source_url":"","keywords":"","description":"","url":"","target":"_self","page_views":30,"is_top":0,"status":0,"create_time":"2017-07-13 23:27:32","update_time":"2019-05-25 00:15:25","get_article_cat":{"cat_name":"配送时效","cat_type":0}},{"article_id":70,"article_cat_id":6,"title":"测试","image":"","source":"","source_url":"","keywords":"","description":"","url":"","target":"_self","page_views":6,"is_top":0,"status":0,"create_time":"2017-07-11 22:04:30","update_time":"2019-05-25 00:15:30","get_article_cat":{"cat_name":"签收与验货","cat_type":0}},{"article_id":69,"article_cat_id":7,"title":"测试","image":"","source":"","source_url":"","keywords":"","description":"","url":"","target":"_self","page_views":2,"is_top":0,"status":0,"create_time":"2017-07-11 22:03:23","update_time":"2017-07-11 22:03:23","get_article_cat":{"cat_name":"支付与账户","cat_type":0}},{"article_id":68,"article_cat_id":8,"title":"测试","image":"","source":"","source_url":"","keywords":"","description":"","url":"","target":"_self","page_views":0,"is_top":0,"status":0,"create_time":"2017-07-11 22:00:44","update_time":"2017-07-11 22:00:44","get_article_cat":{"cat_name":"货到付款","cat_type":0}},{"article_id":67,"article_cat_id":9,"title":"111标题","image":"","source":"百度","source_url":"https:\/\/www.baidu.com","keywords":"","description":"","url":"","target":"_self","page_views":0,"is_top":0,"status":1,"create_time":"2016-12-25 22:52:11","update_time":"2016-12-26 09:25:41","get_article_cat":{"cat_name":"在线支付","cat_type":0}},{"article_id":66,"article_cat_id":1,"title":"标题","image":"","source":"百度","source_url":"https:\/\/www.baidu.com","keywords":"","description":"","url":"","target":"_self","page_views":0,"is_top":0,"status":1,"create_time":"2016-12-25 22:52:11","update_time":"2016-12-26 09:25:41","get_article_cat":{"cat_name":"物流配送","cat_type":0}},{"article_id":64,"article_cat_id":1,"title":"标题","image":"","source":"","source_url":"http:\/\/www.baidu.com","keywords":"","description":"","url":"","target":"_self","page_views":0,"is_top":0,"status":1,"create_time":"2016-12-25 22:51:13","update_time":"2016-12-25 22:51:13","get_article_cat":{"cat_name":"物流配送","cat_type":0}},{"article_id":63,"article_cat_id":1,"title":"标题","image":"","source":"社区","source_url":"http:\/\/www.baidu.com","keywords":"","description":"","url":"","target":"_self","page_views":0,"is_top":0,"status":1,"create_time":"2016-12-25 22:51:06","update_time":"2016-12-25 22:51:06","get_article_cat":{"cat_name":"物流配送","cat_type":0}},{"article_id":62,"article_cat_id":24,"title":"标题","image":"","source":"","source_url":"","keywords":"","description":"","url":"","target":"_self","page_views":1,"is_top":1,"status":1,"create_time":"2016-12-25 22:49:18","update_time":"2017-01-04 15:48:31","get_article_cat":{"cat_name":"购物保障","cat_type":0}},{"article_id":61,"article_cat_id":3,"title":"3G知识普及","image":"","source":"","source_url":"","keywords":"","description":"","url":"","target":"_self","page_views":0,"is_top":1,"status":1,"create_time":"","update_time":"2017-01-04 15:48:31","get_article_cat":{"cat_name":"配送服务","cat_type":0}},{"article_id":60,"article_cat_id":3,"title":"置顶标题","image":"","source":"","source_url":"","keywords":"","description":"","url":"","target":"_self","page_views":0,"is_top":1,"status":1,"create_time":"","update_time":"","get_article_cat":{"cat_name":"配送服务","cat_type":0}},{"article_id":59,"article_cat_id":3,"title":"3G知识普及","image":"","source":"","source_url":"","keywords":"","description":"","url":"","target":"_self","page_views":1,"is_top":0,"status":1,"create_time":"","update_time":"","get_article_cat":{"cat_name":"配送服务","cat_type":0}},{"article_id":58,"article_cat_id":22,"title":"3G知识普及","image":"","source":"","source_url":"","keywords":"","description":"","url":"","target":"_self","page_views":2,"is_top":1,"status":1,"create_time":"","update_time":"","get_article_cat":{"cat_name":"商品评价","cat_type":0}},{"article_id":57,"article_cat_id":1,"title":"测试A","image":"","source":"","source_url":"","keywords":"","description":"","url":"","target":"_self","page_views":1000000009,"is_top":1,"status":0,"create_time":"2017-07-13 23:29:27","update_time":"2017-07-13 23:29:27","get_article_cat":{"cat_name":"物流配送","cat_type":0}},{"article_id":56,"article_cat_id":2,"title":"测试B","image":"","source":"","source_url":"","keywords":"","description":"","url":"","target":"_self","page_views":0,"is_top":1,"status":0,"create_time":"2017-07-13 23:29:23","update_time":"2017-07-13 23:29:23","get_article_cat":{"cat_name":"配送查询","cat_type":0}},{"article_id":55,"article_cat_id":3,"title":"测试C","image":"","source":"","source_url":"","keywords":"","description":"","url":"","target":"_self","page_views":0,"is_top":0,"status":0,"create_time":"2017-07-13 23:27:38","update_time":"2017-07-13 23:27:38","get_article_cat":{"cat_name":"配送服务","cat_type":0}},{"article_id":54,"article_cat_id":4,"title":"测试","image":"","source":"","source_url":"","keywords":"","description":"","url":"","target":"_self","page_views":1,"is_top":0,"status":0,"create_time":"2017-07-13 23:27:36","update_time":"2017-07-13 23:27:36","get_article_cat":{"cat_name":"配送费用","cat_type":0}},{"article_id":53,"article_cat_id":5,"title":"测试","image":"","source":"","source_url":"","keywords":"","description":"","url":"","target":"_self","page_views":1,"is_top":0,"status":0,"create_time":"2017-07-13 23:27:32","update_time":"2017-07-13 23:27:32","get_article_cat":{"cat_name":"配送时效","cat_type":0}},{"article_id":52,"article_cat_id":6,"title":"测试","image":"","source":"","source_url":"","keywords":"","description":"","url":"","target":"_self","page_views":0,"is_top":0,"status":0,"create_time":"2017-07-11 22:04:30","update_time":"2017-07-11 22:04:30","get_article_cat":{"cat_name":"签收与验货","cat_type":0}},{"article_id":51,"article_cat_id":7,"title":"测试","image":"","source":"","source_url":"","keywords":"","description":"","url":"","target":"_self","page_views":0,"is_top":0,"status":0,"create_time":"2017-07-11 22:03:23","update_time":"2017-07-11 22:03:23","get_article_cat":{"cat_name":"支付与账户","cat_type":0}},{"article_id":50,"article_cat_id":8,"title":"测试","image":"","source":"","source_url":"","keywords":"","description":"","url":"","target":"_self","page_views":1,"is_top":0,"status":0,"create_time":"2017-07-11 22:00:44","update_time":"2017-07-11 22:00:44","get_article_cat":{"cat_name":"货到付款","cat_type":0}},{"article_id":49,"article_cat_id":9,"title":"111标题","image":"","source":"百度","source_url":"https:\/\/www.baidu.com","keywords":"","description":"","url":"","target":"_self","page_views":0,"is_top":0,"status":1,"create_time":"2016-12-25 22:52:11","update_time":"2016-12-26 09:25:41","get_article_cat":{"cat_name":"在线支付","cat_type":0}}],"total_result":67}}
